easyask/__init__.py
easyask/__main__.py
easyask/logging_config.py
easyask/server.py
easyask/settings.py
easyask/infras/__init__.py
easyask/infras/chart/__init__.py
easyask/infras/chart/chart.py
easyask/infras/chart/echarts.py
easyask/infras/chart/qwen_echarts.py
easyask/tools/__init__.py
easyask/tools/chart.py
easyask-0.11.0.dist-info/licenses/LICENSE
tests/test_echarts.py
easyask-0.11.0.dist-info/METADATA
easyask-0.11.0.dist-info/WHEEL
easyask-0.11.0.dist-info/top_level.txt
easyask-0.11.0.dist-info/RECORD
