Metadata-Version: 2.4
Name: easyask
Version: 0.11.0
Summary: Generate ECharts option dictionaries
Requires-Python: >=3.12
License-File: LICENSE
Requires-Dist: pytest>=8.4.0
Requires-Dist: mcp[cli]>=1.9.2
Requires-Dist: dashscope>=1.23.4
Requires-Dist: pydantic-settings>=2.9.1
Requires-Dist: colorlog>=6.9.0
Dynamic: license-file
